agentenc/__init__.py
agentenc/base.py
agentenc/op.py
agentenc/rsa.py
AgentEnc-0.1.dist-info/LICENSE
AgentEnc-0.1.dist-info/METADATA
AgentEnc-0.1.dist-info/WHEEL
AgentEnc-0.1.dist-info/top_level.txt
AgentEnc-0.1.dist-info/RECORD
